application/__init__.py
application/application.py
codb-1.2.0.data/scripts/codb
conf/__init__.py
conf/usuario.py
core/__init__.py
core/main.py
core/menu.py
core/pantalla.py
plugins/__init__.py
plugins/mariadb/__init__.py
plugins/theme/__init__.py
plugins/theme/bcolors.py
start/__init__.py
start/welcome.py
ui/__init__.py
ui/login.py
codb-1.2.0.dist-info/METADATA
codb-1.2.0.dist-info/WHEEL
codb-1.2.0.dist-info/top_level.txt
codb-1.2.0.dist-info/RECORD
