Metadata-Version: 2.1
Name: codb
Version: 1.2.0
Summary: Database manager CLI.
Home-page: https://github.com/eadev/codb
Author: Edwin Ariza
Author-email: me@edwinariza.com
License: UNKNOWN
Platform: UNKNOWN
Classifier: Programming Language :: Python :: 3
Classifier: License :: OSI Approved :: MIT License
Classifier: Operating System :: OS Independent
Requires-Dist: pymysql
Requires-Dist: tk
Requires-Dist: tabulate
Requires-Dist: stdiomask
